{
  "persons": [
    {
      "name": "Arto Hellas",
      "number": "040-123456",
      "id": 1
    },
    {
      "name": "Ada Lovelace",
      "number": "39-44-5323523",
      "id": 2
    },
    {
      "name": "Dan Abramov",
      "number": "12-43-234345",
      "id": 3
    },
    {
      "name": "Mary Poppendieck",
      "number": "39-23-6423122",
      "id": 4
    },
    {
      "name": "Poppy Seed",
      "number": "476-8200",
      "id": 9
    },
    {
      "name": "Jim Bob",
      "number": "8",
      "id": 10
    },
    {
      "name": "Billy Bob Brother",
      "number": "67",
      "id": 11
    },
    {
      "name": "Jimmy anderson",
      "number": "78",
      "id": 12
    },
    {
      "name": "Harry the Hearless",
      "number": "3",
      "id": 13
    },
    {
      "name": "Hippo Drome",
      "number": "456",
      "id": 14
    },
    {
      "name": "Johnny Tremain",
      "number": "412-888-9700",
      "id": 15
    },
    {
      "name": "popcycle land",
      "number": "9876554",
      "id": 16
    },
    {
      "name": "JAmie particle",
      "number": "44",
      "id": 17
    },
    {
      "name": "JAmie particles",
      "number": "44",
      "id": 18
    },
    {
      "name": "jimmy the cricket",
      "number": "324",
      "id": 19
    },
    {
      "name": "harold",
      "number": "234",
      "id": 20
    },
    {
      "name": "joe",
      "number": "234",
      "id": 21
    },
    {
      "name": "target the hunter",
      "number": "1-44-78",
      "id": 22
    },
    {
      "name": "Partially hydrated",
      "number": "42",
      "id": 23
    },
    {
      "name": "Particle Physics",
      "number": "Pi",
      "id": 24
    },
    {
      "name": "trial portion",
      "number": "more of the same",
      "id": 25
    },
    {
      "name": "Hipo the hyped",
      "number": "884",
      "id": 26
    }
  ]
}